quizen/__init__.py
quizen/output.py
quizen/quiz.py
quizen-0.2.2.dist-info/LICENSE
quizen-0.2.2.dist-info/METADATA
quizen-0.2.2.dist-info/WHEEL
quizen-0.2.2.dist-info/entry_points.txt
quizen-0.2.2.dist-info/top_level.txt
quizen-0.2.2.dist-info/RECORD
