Metadata-Version: 2.1
Name: quizen
Version: 0.2.2
Summary: Un module pour créer facilement un jeu de quiz
Home-page: https://github.com/Tostenn/Quizen.git
Author: kouya tosten
Author-email: kouyatosten@gmail.com
Classifier: Programming Language :: Python :: 3
Classifier: License :: OSI Approved :: MIT License
Classifier: Operating System :: OS Independent
Requires-Python: >=3.6
License-File: LICENSE
Requires-Dist: rich
